ever_given/__init__.py
ever_given/console.py
ever_given/log_processing.py
ever_given/utils.py
ever_given/wrapper.py
ever_given/engines/__init__.py
ever_given/engines/docker_engine.py
ever_given/engines/singularity_engine.py
ever_given/engines/utils.py
ever_given-0.0.14.dist-info/LICENSE
ever_given-0.0.14.dist-info/METADATA
ever_given-0.0.14.dist-info/WHEEL
ever_given-0.0.14.dist-info/entry_points.txt
ever_given-0.0.14.dist-info/top_level.txt
ever_given-0.0.14.dist-info/RECORD
