Metadata-Version: 2.1
Name: ever-given
Version: 0.0.14
Summary: A small wrapper around the docker sdk
Home-page: https://github.com/samplchallenges/SAMPL-league/tree/main/ever_given
Author: Mike Henry
Author-email: mhenry5@uci.edu
Classifier: Programming Language :: Python :: 3
Classifier: License :: OSI Approved :: Mozilla Public License 2.0 (MPL 2.0)
Classifier: Operating System :: OS Independent
Requires-Python: >=3.6
License-File: LICENSE
Requires-Dist: docker
